winix_api/__init__.py
winix_api/errors.py
winix_api/winix_account.py
winix_api/winix_api.py
winix_api/winix_auth.py
winix_api/winix_auth_response.py
winix_api/winix_types.py
winix_api-0.1.2.dist-info/licenses/LICENSE
winix_api-0.1.2.dist-info/METADATA
winix_api-0.1.2.dist-info/WHEEL
winix_api-0.1.2.dist-info/top_level.txt
winix_api-0.1.2.dist-info/RECORD
