Metadata-Version: 2.4
Name: winix-api
Version: 0.1.2
Summary: Python client for interacting with Winix air purifier devices via the Winix IoT API. Provides authentication, device management, and control.
Author: Chocotonic
License-Expression: MIT
Project-URL: Homepage, https://github.com/Chocotonic/winix-api
Project-URL: Repository, https://github.com/Chocotonic/winix-api
Project-URL: Documentation, https://github.com/Chocotonic/winix-api#readme
Project-URL: License, https://opensource.org/licenses/MIT
Requires-Python: >=3.10
License-File: LICENSE
Requires-Dist: black>=25.12.0
Requires-Dist: pyjwt>=2.10.1
Requires-Dist: pytest-cov>=7.0.0
Requires-Dist: pytest>=9.0.2
Requires-Dist: python-dotenv>=1.2.1
Requires-Dist: requests>=2.32.0
Requires-Dist: warrant-lite>=1.0.4
Dynamic: license-file
